fastapi_toolsets/__init__.py
fastapi_toolsets/cli/__init__.py
fastapi_toolsets/cli/app.py
fastapi_toolsets/cli/commands/__init__.py
fastapi_toolsets/cli/commands/fixtures.py
fastapi_toolsets/crud/__init__.py
fastapi_toolsets/crud/factory.py
fastapi_toolsets/crud/search.py
fastapi_toolsets/db.py
fastapi_toolsets/exceptions/__init__.py
fastapi_toolsets/exceptions/exceptions.py
fastapi_toolsets/exceptions/handler.py
fastapi_toolsets/fixtures/__init__.py
fastapi_toolsets/fixtures/enum.py
fastapi_toolsets/fixtures/registry.py
fastapi_toolsets/fixtures/utils.py
fastapi_toolsets/py.typed
fastapi_toolsets/pytest/__init__.py
fastapi_toolsets/pytest/plugin.py
fastapi_toolsets/pytest/utils.py
fastapi_toolsets/schemas.py
fastapi_toolsets-0.4.1.dist-info/licenses/LICENSE
fastapi_toolsets-0.4.1.dist-info/WHEEL
fastapi_toolsets-0.4.1.dist-info/entry_points.txt
fastapi_toolsets-0.4.1.dist-info/METADATA
fastapi_toolsets-0.4.1.dist-info/RECORD
