Metadata-Version: 2.4
Name: fastapi-toolsets
Version: 0.4.1
Summary: Reusable tools for FastAPI: async CRUD, fixtures, CLI, and standardized responses for SQLAlchemy + PostgreSQL
Keywords: fastapi,sqlalchemy,postgresql
Author: d3vyce
Author-email: d3vyce <contact@d3vyce.fr>
License-Expression: MIT
License-File: LICENSE
Classifier: Development Status :: 4 - Beta
Classifier: Framework :: AsyncIO
Classifier: Framework :: FastAPI
Classifier: Framework :: Pydantic
Classifier: Intended Audience :: Developers
Classifier: Intended Audience :: Information Technology
Classifier: Intended Audience :: System Administrators
Classifier: License :: OSI Approved :: MIT License
Classifier: Operating System :: OS Independent
Classifier: Programming Language :: Python :: 3 :: Only
Classifier: Programming Language :: Python :: 3.11
Classifier: Programming Language :: Python :: 3.12
Classifier: Programming Language :: Python :: 3.13
Classifier: Programming Language :: Python :: 3.14
Classifier: Topic :: Software Development :: Libraries :: Python Modules
Classifier: Topic :: Software Development :: Libraries
Classifier: Topic :: Software Development
Classifier: Typing :: Typed
Requires-Dist: fastapi>=0.100.0
Requires-Dist: sqlalchemy[asyncio]>=2.0
Requires-Dist: asyncpg>=0.29.0
Requires-Dist: pydantic>=2.0
Requires-Dist: typer>=0.9.0
Requires-Dist: httpx>=0.25.0
Requires-Dist: fastapi-toolsets[test] ; extra == 'dev'
Requires-Dist: ruff>=0.1.0 ; extra == 'dev'
Requires-Dist: ty>=0.0.1a0 ; extra == 'dev'
Requires-Dist: pytest>=8.0.0 ; extra == 'test'
Requires-Dist: pytest-anyio>=0.0.0 ; extra == 'test'
Requires-Dist: coverage>=7.0.0 ; extra == 'test'
Requires-Dist: pytest-cov>=4.0.0 ; extra == 'test'
Requires-Python: >=3.11
Project-URL: Homepage, https://github.com/d3vyce/fastapi-toolsets
Project-URL: Documentation, https://fastapi-toolsets.d3vyce.fr/
Project-URL: Repository, https://github.com/d3vyce/fastapi-toolsets
Project-URL: Issues, https://github.com/d3vyce/fastapi-toolsets/issues
Provides-Extra: dev
Provides-Extra: test
